ogoutils/__init__.py
ogoutils/__main__.py
ogoutils/decryption.py
ogoutils/diary.py
ogoutils/encryption.py
ogo_utils-0.1.22.dist-info/entry_points.txt
ogo_utils-0.1.22.dist-info/LICENSE
ogo_utils-0.1.22.dist-info/WHEEL
ogo_utils-0.1.22.dist-info/METADATA
ogo_utils-0.1.22.dist-info/RECORD
