Metadata-Version: 2.1
Name: ogo-utils
Version: 0.1.22
Summary: This project prefer utils for self working
Author: Vasiliy Silver
Author-email: s555133@mail.ru
Requires-Python: >=3.9,<4.0
Classifier: Programming Language :: Python :: 3
Classifier: Programming Language :: Python :: 3.9
Classifier: Programming Language :: Python :: 3.10
Requires-Dist: pyAesCrypt (>=6.0.0,<7.0.0)
Requires-Dist: pytest (>=7.1.3,<8.0.0)
